Metadata-Version: 2.0
Name: leancloud-sdk
Version: 1.11.1
Summary: LeanCloud Python SDK
Home-page: https://leancloud.cn/
Author: asaka
Author-email: lan@leancloud.rocks
License: LGPL
Keywords: Leancloud SDK
Platform: UNKNOWN
Classifier: Development Status :: 5 - Production/Stable
Classifier: Intended Audience :: Developers
Classifier: Programming Language :: Python :: 2
Classifier: Programming Language :: Python :: 2.7
Classifier: Programming Language :: Python :: 3
Classifier: Programming Language :: Python :: 3.5
Requires-Dist: arrow
Requires-Dist: iso8601
Requires-Dist: qiniu
Requires-Dist: requests
Requires-Dist: typing
Requires-Dist: werkzeug
Provides-Extra: dev
Requires-Dist: sphinx; extra == 'dev'
Requires-Dist: sphinx-rtd-theme; extra == 'dev'
Provides-Extra: test
Requires-Dist: flask; extra == 'test'
Requires-Dist: nose; extra == 'test'
Requires-Dist: wsgi-intercept; extra == 'test'
